django_dict_field/__init__.py
django_dict_field/dict_field.py
django_dict_field/serializer.py
django_dict_field-0.1.0a1.dist-info/METADATA
django_dict_field-0.1.0a1.dist-info/WHEEL
django_dict_field-0.1.0a1.dist-info/licenses/LICENSE
django_dict_field-0.1.0a1.dist-info/RECORD
