Metadata-Version: 2.4
Name: django-dict-field
Version: 0.1.0a1
Summary: Django extension for efficient and easy storing dict data in django field.
License-Expression: MIT
License-File: LICENSE
Author: skv0zsneg
Author-email: <klimentlamonov@yandex.ru>
Requires-Python: >=3.10
Classifier: Programming Language :: Python :: 3
Classifier: Programming Language :: Python :: 3.10
Classifier: Programming Language :: Python :: 3.11
Classifier: Programming Language :: Python :: 3.12
Classifier: Programming Language :: Python :: 3.13
Classifier: Programming Language :: Python :: 3.14
Requires-Dist: django (>=4.2.0)
Requires-Dist: msgspec (>=0.20.0,<0.21.0)
